{
  "_fv": 10,
  "_type": "tool",
  "definition": {
    "renderType": 0,
    "texture": "alexandrite2_axe",
    "customModelName": "Normal",
    "name": "Alexandrite Axe",
    "specialInfo": [],
    "creativeTab": {
      "value": "CUSTOM:CustomOreMod"
    },
    "toolType": "Axe",
    "harvestLevel": 7,
    "efficiency": 20.0,
    "attackSpeed": 1.0,
    "enchantability": 33,
    "damageVsEntity": 4.0,
    "usageCount": 3400,
    "blocksAffected": [],
    "hasGlow": false,
    "repairItems": [
      {
        "value": "CUSTOM:Alexandrite"
      }
    ],
    "stayInGridWhenCrafting": false,
    "damageOnCrafting": false
  }
}