{
  "_fv": 10,
  "_type": "recipe",
  "definition": {
    "recipeType": "Crafting",
    "xpReward": 0.0,
    "cookingTime": 200,
    "recipeRetstackSize": 1,
    "group": "",
    "recipeShapeless": false,
    "recipeSlots": [
      {
        "value": ""
      },
      {
        "value": "Items.GOLDEN_APPLE#1"
      },
      {
        "value": ""
      },
      {
        "value": "Blocks.GOLD_BLOCK"
      },
      {
        "value": "Items.EMERALD"
      },
      {
        "value": "Blocks.GOLD_BLOCK"
      },
      {
        "value": ""
      },
      {
        "value": "Blocks.GOLD_BLOCK"
      },
      {
        "value": ""
      }
    ],
    "recipeReturnStack": {
      "value": "Items.TOTEM_OF_UNDYING"
    },
    "name": "totem_of_undying",
    "namespace": "mod"
  }
}